Workbook

Sheet 01 - لوحة القيادة التنفيذية
B2: 🏛️ لوحة الرقابة المالية التنفيذية - محترفو التعليم
B4: إجمالي التحصيل النقدي | C4: إجمالي العمليات الناجحة | D4: التكلفة المباشرة المقدرة | E4: صافي الهامش التشغيلي
B5: =SUM('18 - المعاملات والسجلات التفصيلية'!D:D) | C5: =COUNTA('18 - المعاملات والسجلات التفصيلية'!B:B)-1 | D5: =B5 * '20 - إعدادات وتهيئة النظام'!C2 | E5: =B5 - D5
B6: السيولة التاريخية | C6: سندات مبيع كودات | D6: حصة المدرسين المفترضة | E6: الفائض النقدي الخام

Sheet 02 - الموقف المالي العام

Sheet 03 - تحليلات الإيرادات

Sheet 04 - تقارير الطلاب المالية
A1: الطالب | B1: المسار | C1: المنطقة | D1: المواد | E1: إجمالي الاستحقاق | F1: المدفوع | G1: المتبقي | H1: مؤشر الخطر
A2: دارين شماع | B2: بكالوريا علمي | C2: دمشق | D2: 0 | E2: 0 | F2: 0 | G2: 0 | H2: منخفض
A3: محمد الحجي | B3: بكالوريا علمي | C3: دمشق | D3: 8 | E3: 0 | F3: 0 | G3: 0 | H3: منخفض
A4: ثائر المصري | B4: - | C4: - | D4: 0 | E4: 0 | F4: 0 | G4: 0 | H4: منخفض
A5: Test Student | B5: بكالوريا علمي | C5: دمشق | D5: 0 | E5: 0 | F5: 0 | G5: 0 | H5: منخفض
A6: ثائر المصري | B6: - | C6: - | D6: 2 | E6: 0 | F6: 0 | G6: 0 | H6: منخفض
A7: اكرم حمدان | B7: بكالوريا علمي | C7: دمشق | D7: 0 | E7: 0 | F7: 0 | G7: 0 | H7: منخفض
A8: عبد الله جنيد | B8: بكالوريا علمي | C8: دمشق | D8: 0 | E8: 0 | F8: 0 | G8: 0 | H8: منخفض

Sheet 05 - التقرير المالي للمدرسين
A1: المدرس | B1: الطلاب | C1: الإيراد المحقق | D1: العمولة المتفق عليها | E1: المستحقات المقدرة | F1: حالة الصرف
A2: علي منصور | B2: 1 | C2: 0 | D2: 0.45 | E2: =C2*D2 | F2: معلقة بالتسوية
A3: ثائر المصري | B3: 0 | C3: 0 | D3: 0.45 | E3: =C3*D3 | F3: معلقة بالتسوية
A4: أ. عمار الرياضيات | B4: 0 | C4: 0 | D4: 0.45 | E4: =C4*D4 | F4: معلقة بالتسوية
A5: أ. سامر الرياضيات | B5: 0 | C5: 0 | D5: 0.45 | E5: =C5*D5 | F5: معلقة بالتسوية
A6: أ. نور الفيزياء | B6: 0 | C6: 0 | D6: 0.45 | E6: =C6*D6 | F6: معلقة بالتسوية
A7: أ. لينا العربي | B7: 0 | C7: 0 | D7: 0.45 | E7: =C7*D7 | F7: معلقة بالتسوية
A8: أ. عمر العربي | B8: 0 | C8: 0 | D8: 0.45 | E8: =C8*D8 | F8: معلقة بالتسوية
A9: ثصق | B9: 0 | C9: 0 | D9: 0.45 | E9: =C9*D9 | F9: معلقة بالتسوية

Sheet 06 - أداء الفروع والمراكز

Sheet 07 - ربحية المواد والكورسات
A1: عنوان المادة | B1: المسجلين | C1: الإيراد الكلي | D1: تكلفة المدرس | E1: صافي الربحية | F1: هامش الربح %
A2: ثصقصث | B2: 0 | C2: 0 | D2: =C2 * 0.45 | E2: =C2 - D2 | F2: =IFERROR(E2/C2, 0)
A3: مكثفة اللغة العربية المشتركة - أ. عمر | B3: 0 | C3: 0 | D3: =C3 * 0.45 | E3: =C3 - D3 | F3: =IFERROR(E3/C3, 0)
A4: مكثفة اللغة العربية المشتركة - أ. لينا | B4: 0 | C4: 0 | D4: =C4 * 0.45 | E4: =C4 - D4 | F4: =IFERROR(E4/C4, 0)
A5: مكثفة الفيزياء العلمي | B5: 0 | C5: 0 | D5: =C5 * 0.45 | E5: =C5 - D5 | F5: =IFERROR(E5/C5, 0)
A6: مكثفة الرياضيات العلمي - أ. سامر | B6: 0 | C6: 0 | D6: =C6 * 0.45 | E6: =C6 - D6 | F6: =IFERROR(E6/C6, 0)
A7: مكثفة الرياضيات العلمي - أ. عمار | B7: 0 | C7: 0 | D7: =C7 * 0.45 | E7: =C7 - D7 | F7: =IFERROR(E7/C7, 0)
A8: ????? ????? ??????? ???????? - ?. ??? | B8: 0 | C8: 0 | D8: =C8 * 0.45 | E8: =C8 - D8 | F8: =IFERROR(E8/C8, 0)
A9: ????? ????? ??????? ???????? - ?. ???? | B9: 0 | C9: 0 | D9: =C9 * 0.45 | E9: =C9 - D9 | F9: =IFERROR(E9/C9, 0)
A10: ????? ???????? ?????? | B10: 0 | C10: 0 | D10: =C10 * 0.45 | E10: =C10 - D10 | F10: =IFERROR(E10/C10, 0)
A11: ????? ????????? ?????? - ?. ???? | B11: 0 | C11: 0 | D11: =C11 * 0.45 | E11: =C11 - D11 | F11: =IFERROR(E11/C11, 0)
A12: مكثفة الفيزياء - طريقك للـ 400 | B12: 1 | C12: 0 | D12: =C12 * 0.45 | E12: =C12 - D12 | F12: =IFERROR(E12/C12, 0)
A13: مكثفة الرياضيات - الأستاذ علي منصور | B13: 0 | C13: 0 | D13: =C13 * 0.45 | E13: =C13 - D13 | F13: =IFERROR(E13/C13, 0)

Sheet 08 - تتبع الدفعات والأقساط

Sheet 09 - الديون والذمم المتعثرة

Sheet 10 - الاستحقاقات المالية Accruals

Sheet 11 - كشف عمولات الشركاء

Sheet 12 - تتبع المصروفات التشغيلية

Sheet 13 - قائمة الدخل P&L
B1: 📋 كشف الأرباح والخسائر التشغيلي | C1: التحليل الرقمي
B2: صافي الإيرادات (Net Revenue) | C2: =SUM('18 - المعاملات والسجلات التفصيلية'!D:D)
B3: (-) التكلفة المباشرة للتدريس | C3: =SUM('05 - التقرير المالي للمدرسين'!E:E)
B4: إجمالي هامش المساهمة (Gross Margin) | C4: =C3 - C4
B5: (-) مصاريف النقل والاستضافة (Hosting 3%) | C5: =C3 * '20 - إعدادات وتهيئة النظام'!C3
B6: المصاريف الإدارية التقديرية | C6: 100000
B7: صافي الربح التشغيلي (Net Profit) | C7: =C5 - C6 - C7

Sheet 14 - تقرير التدفق النقدي

Sheet 15 - ملخص الميزانية العمومية
B1: ⚖️ هيكلية المركز المالي | C1: القيمة
B2: السيولة النقدية بالصندوق | C2: 0
B3: ذمم الطلاب المدينة | C3: =SUM('04 - تقارير الطلاب المالية'!G:G)
B4: 👉 إجمالي الأصول المتداولة | C4: =C3 + C4
B5: التزامات مستحقة للمدرسين | C5: =SUM('05 - التقرير المالي للمدرسين'!E:E)
B6: الأرباح المحتجزة (Equity) | C6: ='13 - قائمة الدخل P&L'!C8
B7: 👉 إجمالي الخصوم وحقوق الملكية | C7: =C6 + C7

Sheet 16 - التوقعات المالية Forecasting

Sheet 17 - مؤشرات الأداء الذكية KPI

Sheet 18 - المعاملات والسجلات التفصيلية
A1: التاريخ | B1: كود العملية | C1: المنتج التعليمي | D1: صافي المقبوض | E1: جهة التحصيل | F1: اسم الطالب | G1: النوع
A2: - | B2: AML-JVOQ-7GMY | C2: مكثفة الفيزياء - طريقك للـ 400 | D2: 0 | E2: مكتبة الأمل | F2: - | G2: Course
A3: - | B3: SCI-PKG-DEMO-2026 | C3: باقة العلمي التجريبية مع المواد المشتركة | D3: 0 | E3: بيع مباشر | F3: - | G3: Package

Sheet 19 - التنبيهات المالية الذكية
A1: المؤشر والمنبه | B1: الحالة الحالية
A2: تحقيق هدف المبيعات | B2: =IF('01 - لوحة القيادة التنفيذية'!B5 < '20 - إعدادات وتهيئة النظام'!C4, "🚨 دون المستهدف", "✅ متوافق مع الخطة")

Sheet 20 - إعدادات وتهيئة النظام
B1: 🛠️ تهيئة المتغيرات المالية للنظام | C1: القيمة
B2: نسبة عمولة المدرس الافتراضية | C2: 0.45
B3: نسبة مصروف التشغيل (CDN/IT) | C3: 0.03
B4: هدف الإيراد الشهري المرجعي | C4: 5000000

Sheet 21 - قاعدة بيانات الربط
